README.md
setup.py
wbsync/__init__.py
wbsync.egg-info/PKG-INFO
wbsync.egg-info/SOURCES.txt
wbsync.egg-info/dependency_links.txt
wbsync.egg-info/requires.txt
wbsync.egg-info/top_level.txt
wbsync/external/__init__.py
wbsync/external/uri_factory.py
wbsync/synchronization/__init__.py
wbsync/synchronization/algorithms.py
wbsync/synchronization/ontology_synchronizer.py
wbsync/synchronization/operations.py
wbsync/triplestore/__init__.py
wbsync/triplestore/triple_info.py
wbsync/triplestore/triplestore_manager.py
wbsync/triplestore/wikibase_adapter.py
wbsync/util/__init__.py
wbsync/util/error.py
wbsync/util/mappings.py
wbsync/util/uri_constants.py