Metadata-Version: 2.1
Name: wbsync
Version: 0.1.4
Summary: UNKNOWN
Home-page: https://github.com/weso/rdf-wb-sync
Author: Alejandro González Hevia, Othmane Bakhtaoui, Pablo Menéndez
Author-email: alejandrgh11@gmail.com, b.othmane98@live.fr
License: MIT
Platform: UNKNOWN
Classifier: Intended Audience :: Developers
Classifier: License :: OSI Approved :: MIT License
Classifier: Programming Language :: Python :: 3
Classifier: Programming Language :: Python :: 3.6
Classifier: Programming Language :: Python :: 3.7
